{
  "serviceTypes": [
    {
      "serviceTypeName": "/score/MapApiLanesStamped",
      "version": {
        "major": 1,
        "minor": 0
      },
      "bindings": [
        {
          "binding": "SHM",
          "serviceId": 6432,
          "events": [
            {
              "eventName": "map_api_lanes_stamped",
              "eventId": 1
            },
            {
              "eventName": "dummy_data_stamped",
              "eventId": 2
            }
          ]
        }
      ]
    }
  ],
  "serviceInstances": [
    {
      "instanceSpecifier": "score/MapApiLanesStamped",
      "serviceTypeName": "/score/MapApiLanesStamped",
      "version": {
        "major": 1,
        "minor": 0
      },
      "instances": [
        {
          "instanceId": 1,
          "allowedConsumer": {
            "QM": [
              4002,
              0
            ]
          },
          "allowedProvider": {
            "QM": [
              4001,
              0
            ]
          },
          "asil-level": "QM",
          "binding": "SHM",
          "events": [
            {
              "eventName": "map_api_lanes_stamped",
              "numberOfSampleSlots": 10,
              "maxSubscribers": 3
            }
          ]
        }
      ]
    }
  ]
}
